wtd/cli.py
wiredtiger_debug_tools-0.1.3.dist-info/LICENSE
wiredtiger_debug_tools-0.1.3.dist-info/METADATA
wiredtiger_debug_tools-0.1.3.dist-info/WHEEL
wiredtiger_debug_tools-0.1.3.dist-info/entry_points.txt
wiredtiger_debug_tools-0.1.3.dist-info/RECORD
