Metadata-Version: 2.1
Name: wiredtiger-debug-tools
Version: 0.1.3
Summary: Collections of tools to debug and analyze MongoDB WiredTiger files
Author: Tommaso Tocci
Author-email: tommaso.tocci@mongodb.com
Requires-Python: >=3.10,<4.0
Classifier: Programming Language :: Python :: 3
Classifier: Programming Language :: Python :: 3.10
Classifier: Programming Language :: Python :: 3.11
Requires-Dist: click (>=8.1.7,<9.0.0)
Requires-Dist: pymongo (>=4.8.0,<5.0.0)
Requires-Dist: rich (>=13.7.1,<14.0.0)
